canonicalwebteam/__init__.py
canonicalwebteam/docstring_extractor/__init__.py
canonicalwebteam_docstring_extractor-1.2.0.dist-info/LICENSE
canonicalwebteam_docstring_extractor-1.2.0.dist-info/WHEEL
canonicalwebteam_docstring_extractor-1.2.0.dist-info/METADATA
canonicalwebteam_docstring_extractor-1.2.0.dist-info/RECORD
