Metadata-Version: 2.1
Name: canonicalwebteam-docstring-extractor
Version: 1.2.0
Summary: Get Python docstrings from files
Home-page: https://github.com/canonical-web-and-design/canonicalwebteam.docstring-extractor
License: GPL-3.0-or-later
Keywords: docstring,docstrings,parser
Author: Canonical Web Team
Author-email: webteam@canonical.com
Requires-Python: >=3.8,<4.0
Classifier: License :: OSI Approved :: GNU General Public License v3 or later (GPLv3+)
Classifier: Programming Language :: Python :: 3
Classifier: Programming Language :: Python :: 3.8
Classifier: Programming Language :: Python :: 3.9
Classifier: Programming Language :: Python :: 3.10
Classifier: Programming Language :: Python :: 3.11
Classifier: Topic :: Software Development :: Libraries :: Python Modules
Requires-Dist: docstring-parser (>=0.14.1,<0.15.0)
Project-URL: Documentation, https://github.com/canonical-web-and-design/canonicalwebteam.docstring-extractor
Project-URL: Repository, https://github.com/canonical-web-and-design/canonicalwebteam.docstring-extractor
